{"fertilityList": [{"year": 1950, "15-19": null, "20-24": null, "25-29": null, "30-34": null, "35-39": null, "40-44": null, "45-49": null, "Oceania": null, "Place": "Oceania", "Gross Reproduction Rate": null, "Mortality Rate under 5": null, "Mortality Rate under 5 male": null, "Mortality Rate under 5 female": null}, {"year": 1951, "15-19": null, "20-24": null, "25-29": null, "30-34": null, "35-39": null, "40-44": null, "45-49": null, "Oceania": null, "Place": "Oceania", "Gross Reproduction Rate": null, "Mortality Rate under 5": null, "Mortality Rate under 5 male": null, "Mortality Rate under 5 female": null}, {"year": 1952, "15-19": null, "20-24": null, "25-29": null, "30-34": null, "35-39": null, "40-44": null, "45-49": null, "Oceania": null, "Place": "Oceania", "Gross Reproduction Rate": null, "Mortality Rate under 5": null, "Mortality Rate under 5 male": null, "Mortality Rate under 5 female": null}, {"year": 1953, "15-19": null, "20-24": null, "25-29": null, "30-34": null, "35-39": null, "40-44": null, "45-49": null, "Oceania": null, "Place": "Oceania", "Gross Reproduction Rate": null, "Mortality Rate under 5": null, "Mortality Rate under 5 male": null, "Mortality Rate under 5 female": null}, {"year": 1954, "15-19": null, "20-24": null, "25-29": null, "30-34": null, "35-39": null, "40-44": null, "45-49": null, "Oceania": null, "Place": "Oceania", "Gross Reproduction Rate": null, "Mortality Rate under 5": null, "Mortality Rate under 5 male": null, "Mortality Rate under 5 female": null}, {"year": 1955, "15-19": null, "20-24": null, "25-29": null, "30-34": null, "35-39": null, "40-44": null, "45-49": null, "Oceania": null, "Place": "Oceania", "Gross Reproduction Rate": null, "Mortality Rate under 5": null, "Mortality Rate under 5 male": null, "Mortality Rate under 5 female": null}, {"year": 1956, "15-19": null, "20-24": null, "25-29": null, "30-34": null, "35-39": null, "40-44": null, "45-49": null, "Oceania": null, "Place": "Oceania", "Gross Reproduction Rate": null, "Mortality Rate under 5": null, "Mortality Rate under 5 male": null, "Mortality Rate under 5 female": null}, {"year": 1957, "15-19": null, "20-24": null, "25-29": null, "30-34": null, "35-39": null, "40-44": null, "45-49": null, "Oceania": null, "Place": "Oceania", "Gross Reproduction Rate": null, "Mortality Rate under 5": null, "Mortality Rate under 5 male": null, "Mortality Rate under 5 female": null}, {"year": 1958, "15-19": null, "20-24": null, "25-29": null, "30-34": null, "35-39": null, "40-44": null, "45-49": null, "Oceania": null, "Place": "Oceania", "Gross Reproduction Rate": null, "Mortality Rate under 5": null, "Mortality Rate under 5 male": null, "Mortality Rate under 5 female": null}, {"year": 1959, "15-19": null, "20-24": null, "25-29": null, "30-34": null, "35-39": null, "40-44": null, "45-49": null, "Oceania": null, "Place": "Oceania", "Gross Reproduction Rate": null, "Mortality Rate under 5": null, "Mortality Rate under 5 male": null, "Mortality Rate under 5 female": null}, {"year": 1960, "15-19": null, "20-24": null, "25-29": null, "30-34": null, "35-39": null, "40-44": null, "45-49": null, "Oceania": null, "Place": "Oceania", "Gross Reproduction Rate": null, "Mortality Rate under 5": null, "Mortality Rate under 5 male": null, "Mortality Rate under 5 female": null}, {"year": 1961, "15-19": null, "20-24": null, "25-29": null, "30-34": null, "35-39": null, "40-44": null, "45-49": null, "Oceania": null, "Place": "Oceania", "Gross Reproduction Rate": null, "Mortality Rate under 5": null, "Mortality Rate under 5 male": null, "Mortality Rate under 5 female": null}, {"year": 1962, "15-19": null, "20-24": null, "25-29": null, "30-34": null, "35-39": null, "40-44": null, "45-49": null, "Oceania": null, "Place": "Oceania", "Gross Reproduction Rate": null, "Mortality Rate under 5": null, "Mortality Rate under 5 male": null, "Mortality Rate under 5 female": null}, {"year": 1963, "15-19": null, "20-24": null, "25-29": null, "30-34": null, "35-39": null, "40-44": null, "45-49": null, "Oceania": null, "Place": "Oceania", "Gross Reproduction Rate": null, "Mortality Rate under 5": null, "Mortality Rate under 5 male": null, "Mortality Rate under 5 female": null}, {"year": 1964, "15-19": null, "20-24": null, "25-29": null, "30-34": null, "35-39": null, "40-44": null, "45-49": null, "Oceania": null, "Place": "Oceania", "Gross Reproduction Rate": null, "Mortality Rate under 5": null, "Mortality Rate under 5 male": null, "Mortality Rate under 5 female": null}, {"year": 1965, "15-19": null, "20-24": null, "25-29": null, "30-34": null, "35-39": null, "40-44": null, "45-49": null, "Oceania": null, "Place": "Oceania", "Gross Reproduction Rate": null, "Mortality Rate under 5": null, "Mortality Rate under 5 male": null, "Mortality Rate under 5 female": null}, {"year": 1966, "15-19": null, "20-24": null, "25-29": null, "30-34": null, "35-39": null, "40-44": null, "45-49": null, "Oceania": null, "Place": "Oceania", "Gross Reproduction Rate": null, "Mortality Rate under 5": null, "Mortality Rate under 5 male": null, "Mortality Rate under 5 female": null}, {"year": 1967, "15-19": null, "20-24": null, "25-29": null, "30-34": null, "35-39": null, "40-44": null, "45-49": null, "Oceania": null, "Place": "Oceania", "Gross Reproduction Rate": null, "Mortality Rate under 5": null, "Mortality Rate under 5 male": null, "Mortality Rate under 5 female": null}, {"year": 1968, "15-19": null, "20-24": null, "25-29": null, "30-34": null, "35-39": null, "40-44": null, "45-49": null, "Oceania": null, "Place": "Oceania", "Gross Reproduction Rate": null, "Mortality Rate under 5": null, "Mortality Rate under 5 male": null, "Mortality Rate under 5 female": null}, {"year": 1969, "15-19": null, "20-24": null, "25-29": null, "30-34": null, "35-39": null, "40-44": null, "45-49": null, "Oceania": null, "Place": "Oceania", "Gross Reproduction Rate": null, "Mortality Rate under 5": null, "Mortality Rate under 5 male": null, "Mortality Rate under 5 female": null}, {"year": 1970, "15-19": null, "20-24": null, "25-29": null, "30-34": null, "35-39": null, "40-44": null, "45-49": null, "Oceania": null, "Place": "Oceania", "Gross Reproduction Rate": null, "Mortality Rate under 5": null, "Mortality Rate under 5 male": null, "Mortality Rate under 5 female": null}, {"year": 1971, "15-19": null, "20-24": null, "25-29": null, "30-34": null, "35-39": null, "40-44": null, "45-49": null, "Oceania": null, "Place": "Oceania", "Gross Reproduction Rate": null, "Mortality Rate under 5": null, "Mortality Rate under 5 male": null, "Mortality Rate under 5 female": null}, {"year": 1972, "15-19": null, "20-24": null, "25-29": null, "30-34": null, "35-39": null, "40-44": null, "45-49": null, "Oceania": null, "Place": "Oceania", "Gross Reproduction Rate": null, "Mortality Rate under 5": null, "Mortality Rate under 5 male": null, "Mortality Rate under 5 female": null}, {"year": 1973, "15-19": null, "20-24": null, "25-29": null, "30-34": null, "35-39": null, "40-44": null, "45-49": null, "Oceania": null, "Place": "Oceania", "Gross Reproduction Rate": null, "Mortality Rate under 5": null, "Mortality Rate under 5 male": null, "Mortality Rate under 5 female": null}, {"year": 1974, "15-19": null, "20-24": null, "25-29": null, "30-34": null, "35-39": null, "40-44": null, "45-49": null, "Oceania": null, "Place": "Oceania", "Gross Reproduction Rate": null, "Mortality Rate under 5": null, "Mortality Rate under 5 male": null, "Mortality Rate under 5 female": null}, {"year": 1975, "15-19": null, "20-24": null, "25-29": null, "30-34": null, "35-39": null, "40-44": null, "45-49": null, "Oceania": null, "Place": "Oceania", "Gross Reproduction Rate": null, "Mortality Rate under 5": null, "Mortality Rate under 5 male": null, "Mortality Rate under 5 female": null}, {"year": 1976, "15-19": 149.6, "20-24": 330.3, "25-29": 345.8, "30-34": 295.3, "35-39": 225.4, "40-44": 116.8, "45-49": 39.4, "Oceania": 7.513, "Place": "Oceania", "Gross Reproduction Rate": 3.6652, "Mortality Rate under 5": 73.74, "Mortality Rate under 5 male": 80.63, "Mortality Rate under 5 female": 66.51}, {"year": 1977, "15-19": 144.2, "20-24": 320.0, "25-29": 337.1, "30-34": 287.6, "35-39": 218.2, "40-44": 112.8, "45-49": 38.0, "Oceania": 7.2897, "Place": "Oceania", "Gross Reproduction Rate": 3.5561, "Mortality Rate under 5": 71.47, "Mortality Rate under 5 male": 78.21, "Mortality Rate under 5 female": 64.38}, {"year": 1978, "15-19": 138.9, "20-24": 309.8, "25-29": 328.3, "30-34": 280.0, "35-39": 211.0, "40-44": 108.8, "45-49": 36.5, "Oceania": 7.0665, "Place": "Oceania", "Gross Reproduction Rate": 3.447, "Mortality Rate under 5": 69.27, "Mortality Rate under 5 male": 75.87, "Mortality Rate under 5 female": 62.32}, {"year": 1979, "15-19": 80.75, "20-24": 244.25, "25-29": 266.8, "30-34": 198.15, "35-39": 129.9, "40-44": 55.9, "45-49": 20.05, "Oceania": 4.979100000000001, "Place": "Oceania", "Gross Reproduction Rate": 2.42555, "Mortality Rate under 5": 71.005, "Mortality Rate under 5 male": 78.555, "Mortality Rate under 5 female": 63.074999999999996}, {"year": 1980, "15-19": 82.33333333333333, "20-24": 250.46666666666667, "25-29": 268.2, "30-34": 204.36666666666665, "35-39": 132.23333333333332, "40-44": 67.93333333333334, "45-49": 26.599999999999998, "Oceania": 5.160466666666666, "Place": "Oceania", "Gross Reproduction Rate": 2.5159333333333334, "Mortality Rate under 5": 87.73, "Mortality Rate under 5 male": 91.03333333333335, "Mortality Rate under 5 female": 84.24333333333334}, {"year": 1981, "15-19": 81.56666666666666, "20-24": 250.16666666666666, "25-29": 268.3333333333333, "30-34": 203.9, "35-39": 131.4, "40-44": 67.13333333333334, "45-49": 26.299999999999997, "Oceania": 5.144, "Place": "Oceania", "Gross Reproduction Rate": 2.508766666666667, "Mortality Rate under 5": 85.97333333333334, "Mortality Rate under 5 male": 89.41333333333334, "Mortality Rate under 5 female": 82.32}, {"year": 1982, "15-19": 80.86666666666666, "20-24": 249.83333333333337, "25-29": 268.46666666666664, "30-34": 203.4, "35-39": 130.53333333333333, "40-44": 66.36666666666666, "45-49": 26.03333333333333, "Oceania": 5.1275, "Place": "Oceania", "Gross Reproduction Rate": 2.5016333333333334, "Mortality Rate under 5": 84.55, "Mortality Rate under 5 male": 88.10000000000001, "Mortality Rate under 5 female": 80.81}, {"year": 1983, "15-19": 77.91999999999999, "20-24": 234.34, "25-29": 242.61999999999998, "30-34": 173.6, "35-39": 107.05999999999999, "40-44": 50.82, "45-49": 16.66, "Oceania": 4.5151200000000005, "Place": "Oceania", "Gross Reproduction Rate": 2.20196, "Mortality Rate under 5": 64.07, "Mortality Rate under 5 male": 68.96000000000001, "Mortality Rate under 5 female": 58.922000000000004}, {"year": 1984, "15-19": 76.47999999999999, "20-24": 233.14000000000001, "25-29": 239.8, "30-34": 172.28000000000003, "35-39": 105.78, "40-44": 49.14, "45-49": 16.42, "Oceania": 4.464840000000001, "Place": "Oceania", "Gross Reproduction Rate": 2.17784, "Mortality Rate under 5": 62.94200000000001, "Mortality Rate under 5 male": 67.736, "Mortality Rate under 5 female": 57.902}, {"year": 1985, "15-19": 74.01666666666667, "20-24": 230.0666666666667, "25-29": 238.20000000000002, "30-34": 177.30000000000004, "35-39": 112.93333333333334, "40-44": 50.35, "45-49": 15.916666666666666, "Oceania": 4.494183333333333, "Place": "Oceania", "Gross Reproduction Rate": 2.1916, "Mortality Rate under 5": 74.065, "Mortality Rate under 5 male": 80.08166666666666, "Mortality Rate under 5 female": 67.75333333333333}, {"year": 1986, "15-19": 60.10000000000001, "20-24": 198.34, "25-29": 220.1, "30-34": 165.56, "35-39": 96.94999999999999, "40-44": 41.62, "45-49": 13.280000000000001, "Oceania": 3.97969, "Place": "Oceania", "Gross Reproduction Rate": 1.9447400000000001, "Mortality Rate under 5": 52.80500000000001, "Mortality Rate under 5 male": 57.013999999999996, "Mortality Rate under 5 female": 48.387}, {"year": 1987, "15-19": 59.25, "20-24": 194.64, "25-29": 217.19999999999996, "30-34": 164.02000000000004, "35-39": 95.74, "40-44": 40.9, "45-49": 12.959999999999999, "Oceania": 3.9235700000000002, "Place": "Oceania", "Gross Reproduction Rate": 1.9150800000000001, "Mortality Rate under 5": 51.964, "Mortality Rate under 5 male": 56.093, "Mortality Rate under 5 female": 47.627}, {"year": 1988, "15-19": 67.79090909090908, "20-24": 208.2727272727273, "25-29": 225.6818181818182, "30-34": 167.86363636363635, "35-39": 98.65454545454544, "40-44": 42.845454545454544, "45-49": 11.52727272727273, "Oceania": 4.113327272727273, "Place": "Oceania", "Gross Reproduction Rate": 2.008436363636364, "Mortality Rate under 5": 51.93454545454545, "Mortality Rate under 5 male": 55.622727272727275, "Mortality Rate under 5 female": 48.07454545454545}, {"year": 1989, "15-19": 63.92727272727273, "20-24": 203.45454545454547, "25-29": 219.9818181818182, "30-34": 166.19090909090912, "35-39": 96.62727272727274, "40-44": 39.71818181818182, "45-49": 11.58181818181818, "Oceania": 4.0075, "Place": "Oceania", "Gross Reproduction Rate": 1.9578636363636364, "Mortality Rate under 5": 50.84363636363637, "Mortality Rate under 5 male": 54.568181818181806, "Mortality Rate under 5 female": 46.940909090909095}, {"year": 1990, "15-19": 65.41666666666667, "20-24": 197.1916666666667, "25-29": 211.21666666666667, "30-34": 159.225, "35-39": 91.98333333333333, "40-44": 39.5, "45-49": 10.258333333333333, "Oceania": 3.874008333333333, "Place": "Oceania", "Gross Reproduction Rate": 1.890725, "Mortality Rate under 5": 46.74583333333334, "Mortality Rate under 5 male": 50.23166666666666, "Mortality Rate under 5 female": 43.08583333333333}, {"year": 1991, "15-19": 66.46153846153847, "20-24": 190.13846153846154, "25-29": 202.0230769230769, "30-34": 154.05384615384617, "35-39": 87.70769230769231, "40-44": 36.1, "45-49": 9.553846153846154, "Oceania": 3.7308461538461546, "Place": "Oceania", "Gross Reproduction Rate": 1.8206615384615383, "Mortality Rate under 5": 44.77923076923077, "Mortality Rate under 5 male": 48.41692307692308, "Mortality Rate under 5 female": 40.96923076923077}, {"year": 1992, "15-19": 66.05, "20-24": 186.94285714285712, "25-29": 203.53571428571428, "30-34": 154.30714285714288, "35-39": 86.26428571428572, "40-44": 35.16428571428572, "45-49": 9.378571428571428, "Oceania": 3.708492857142857, "Place": "Oceania", "Gross Reproduction Rate": 1.807192857142857, "Mortality Rate under 5": 41.644285714285715, "Mortality Rate under 5 male": 45.27357142857142, "Mortality Rate under 5 female": 37.82857142857143}, {"year": 1993, "15-19": 65.24285714285715, "20-24": 182.37142857142857, "25-29": 199.1142857142857, "30-34": 150.64285714285714, "35-39": 86.3142857142857, "40-44": 34.228571428571435, "45-49": 8.95, "Oceania": 3.6346214285714287, "Place": "Oceania", "Gross Reproduction Rate": 1.7711785714285715, "Mortality Rate under 5": 40.223571428571425, "Mortality Rate under 5 male": 43.91857142857142, "Mortality Rate under 5 female": 36.32785714285714}, {"year": 1994, "15-19": 62.306666666666665, "20-24": 185.56666666666663, "25-29": 199.20000000000002, "30-34": 155.14, "35-39": 88.90666666666667, "40-44": 37.553333333333335, "45-49": 10.353333333333333, "Oceania": 3.6954999999999996, "Place": "Oceania", "Gross Reproduction Rate": 1.7955466666666664, "Mortality Rate under 5": 40.282666666666664, "Mortality Rate under 5 male": 43.70933333333333, "Mortality Rate under 5 female": 36.64533333333334}, {"year": 1995, "15-19": 62.00000000000001, "20-24": 181.10000000000002, "25-29": 196.36, "30-34": 154.50666666666666, "35-39": 91.53333333333333, "40-44": 37.233333333333334, "45-49": 9.886666666666667, "Oceania": 3.663326666666667, "Place": "Oceania", "Gross Reproduction Rate": 1.7940066666666665, "Mortality Rate under 5": 38.773333333333326, "Mortality Rate under 5 male": 41.97533333333333, "Mortality Rate under 5 female": 35.452666666666666}, {"year": 1996, "15-19": 58.1625, "20-24": 175.26875, "25-29": 192.825, "30-34": 157.6125, "35-39": 90.91875000000002, "40-44": 37.681250000000006, "45-49": 9.762499999999998, "Oceania": 3.6113875, "Place": "Oceania", "Gross Reproduction Rate": 1.75131875, "Mortality Rate under 5": 35.85625, "Mortality Rate under 5 male": 38.76625000000001, "Mortality Rate under 5 female": 32.75000000000001}, {"year": 1997, "15-19": 56.48125, "20-24": 171.93750000000003, "25-29": 190.92500000000004, "30-34": 155.4875, "35-39": 92.075, "40-44": 38.1875, "45-49": 8.78125, "Oceania": 3.5696625, "Place": "Oceania", "Gross Reproduction Rate": 1.7449, "Mortality Rate under 5": 34.436875, "Mortality Rate under 5 male": 37.371874999999996, "Mortality Rate under 5 female": 31.365625}, {"year": 1998, "15-19": 53.0625, "20-24": 164.26875, "25-29": 183.95, "30-34": 149.93750000000003, "35-39": 89.39999999999999, "40-44": 36.487500000000004, "45-49": 8.29375, "Oceania": 3.4271249999999998, "Place": "Oceania", "Gross Reproduction Rate": 1.6644375, "Mortality Rate under 5": 33.449375, "Mortality Rate under 5 male": 36.214999999999996, "Mortality Rate under 5 female": 30.504374999999996}, {"year": 1999, "15-19": 52.36470588235294, "20-24": 162.56470588235294, "25-29": 190.18235294117648, "30-34": 152.55294117647057, "35-39": 89.28235294117647, "40-44": 37.788235294117655, "45-49": 9.200000000000001, "Oceania": 3.4698470588235297, "Place": "Oceania", "Gross Reproduction Rate": 1.6964764705882354, "Mortality Rate under 5": 33.205882352941174, "Mortality Rate under 5 male": 35.8235294117647, "Mortality Rate under 5 female": 30.472352941176467}, {"year": 2000, "15-19": 51.75500000000001, "20-24": 157.76999999999998, "25-29": 178.76500000000001, "30-34": 143.85, "35-39": 84.79499999999999, "40-44": 34.61, "45-49": 7.67, "Oceania": 3.2964600000000006, "Place": "Oceania", "Gross Reproduction Rate": 1.6083349999999998, "Mortality Rate under 5": 28.794999999999998, "Mortality Rate under 5 male": 31.293500000000005, "Mortality Rate under 5 female": 26.166999999999994}, {"year": 2001, "15-19": 50.52499999999999, "20-24": 154.605, "25-29": 180.23, "30-34": 143.175, "35-39": 84.225, "40-44": 34.355, "45-49": 7.215000000000001, "Oceania": 3.272005, "Place": "Oceania", "Gross Reproduction Rate": 1.601605, "Mortality Rate under 5": 28.248, "Mortality Rate under 5 male": 30.492499999999996, "Mortality Rate under 5 female": 25.916500000000003}, {"year": 2002, "15-19": 46.545, "20-24": 146.84000000000003, "25-29": 169.81, "30-34": 137.77500000000003, "35-39": 82.1, "40-44": 32.675, "45-49": 7.2700000000000005, "Oceania": 3.1153850000000007, "Place": "Oceania", "Gross Reproduction Rate": 1.529785, "Mortality Rate under 5": 27.514499999999998, "Mortality Rate under 5 male": 29.9075, "Mortality Rate under 5 female": 25.053499999999996}, {"year": 2003, "15-19": 44.845, "20-24": 145.31, "25-29": 171.70999999999998, "30-34": 137.14500000000004, "35-39": 81.67999999999999, "40-44": 31.9, "45-49": 7.580000000000001, "Oceania": 3.1010549999999997, "Place": "Oceania", "Gross Reproduction Rate": 1.52185, "Mortality Rate under 5": 26.526999999999997, "Mortality Rate under 5 male": 28.8995, "Mortality Rate under 5 female": 24.082}, {"year": 2004, "15-19": 43.80499999999999, "20-24": 141.84499999999997, "25-29": 168.07, "30-34": 135.985, "35-39": 78.82, "40-44": 31.48, "45-49": 7.175, "Oceania": 3.03613, "Place": "Oceania", "Gross Reproduction Rate": 1.490295, "Mortality Rate under 5": 25.291500000000006, "Mortality Rate under 5 male": 27.527500000000003, "Mortality Rate under 5 female": 22.990000000000002}, {"year": 2005, "15-19": 42.305, "20-24": 138.35999999999999, "25-29": 164.41, "30-34": 134.055, "35-39": 77.89000000000001, "40-44": 30.805, "45-49": 6.885, "Oceania": 2.97381, "Place": "Oceania", "Gross Reproduction Rate": 1.459565, "Mortality Rate under 5": 24.839000000000006, "Mortality Rate under 5 male": 27.204500000000007, "Mortality Rate under 5 female": 22.400499999999997}, {"year": 2006, "15-19": 41.75499999999999, "20-24": 136.32999999999998, "25-29": 164.815, "30-34": 136.935, "35-39": 78.24499999999998, "40-44": 30.725, "45-49": 6.6899999999999995, "Oceania": 2.977735, "Place": "Oceania", "Gross Reproduction Rate": 1.46179, "Mortality Rate under 5": 24.012000000000004, "Mortality Rate under 5 male": 26.151, "Mortality Rate under 5 female": 21.811999999999998}, {"year": 2007, "15-19": 40.92999999999999, "20-24": 133.445, "25-29": 162.26500000000001, "30-34": 135.13000000000002, "35-39": 76.04000000000002, "40-44": 29.815000000000005, "45-49": 6.51, "Oceania": 2.9207099999999997, "Place": "Oceania", "Gross Reproduction Rate": 1.4338450000000003, "Mortality Rate under 5": 23.305500000000002, "Mortality Rate under 5 male": 25.509, "Mortality Rate under 5 female": 21.032499999999995}, {"year": 2008, "15-19": 39.760000000000005, "20-24": 130.86, "25-29": 159.84, "30-34": 132.36, "35-39": 74.845, "40-44": 29.064999999999998, "45-49": 6.28, "Oceania": 2.8651900000000006, "Place": "Oceania", "Gross Reproduction Rate": 1.4069700000000003, "Mortality Rate under 5": 22.449999999999996, "Mortality Rate under 5 male": 24.5665, "Mortality Rate under 5 female": 20.2635}, {"year": 2009, "15-19": 38.21, "20-24": 127.09500000000003, "25-29": 157.295, "30-34": 130.155, "35-39": 72.845, "40-44": 28.170000000000005, "45-49": 6.055, "Oceania": 2.79939, "Place": "Oceania", "Gross Reproduction Rate": 1.37427, "Mortality Rate under 5": 21.720999999999997, "Mortality Rate under 5 male": 23.778, "Mortality Rate under 5 female": 19.602000000000004}, {"year": 2010, "15-19": 36.85999999999999, "20-24": 123.755, "25-29": 154.91500000000002, "30-34": 128.045, "35-39": 70.92, "40-44": 27.284999999999997, "45-49": 5.825, "Oceania": 2.73818, "Place": "Oceania", "Gross Reproduction Rate": 1.3440150000000002, "Mortality Rate under 5": 21.021, "Mortality Rate under 5 male": 23.029999999999998, "Mortality Rate under 5 female": 18.95}, {"year": 2011, "15-19": 35.73999999999999, "20-24": 121.08999999999999, "25-29": 153.15000000000003, "30-34": 126.37, "35-39": 69.385, "40-44": 26.564999999999998, "45-49": 5.665, "Oceania": 2.689925, "Place": "Oceania", "Gross Reproduction Rate": 1.3208849999999999, "Mortality Rate under 5": 20.3515, "Mortality Rate under 5 male": 22.3105, "Mortality Rate under 5 female": 18.329500000000003}, {"year": 2012, "15-19": 34.644999999999996, "20-24": 118.46, "25-29": 151.36499999999998, "30-34": 124.755, "35-39": 67.905, "40-44": 25.860000000000003, "45-49": 5.484999999999999, "Oceania": 2.642675, "Place": "Oceania", "Gross Reproduction Rate": 1.2975049999999997, "Mortality Rate under 5": 19.704, "Mortality Rate under 5 male": 21.615000000000002, "Mortality Rate under 5 female": 17.732499999999998}, {"year": 2013, "15-19": 33.535000000000004, "20-24": 115.83500000000001, "25-29": 149.57999999999998, "30-34": 123.15500000000004, "35-39": 66.43, "40-44": 25.165, "45-49": 5.3149999999999995, "Oceania": 2.5954050000000004, "Place": "Oceania", "Gross Reproduction Rate": 1.2744149999999999, "Mortality Rate under 5": 19.0815, "Mortality Rate under 5 male": 20.945, "Mortality Rate under 5 female": 17.157999999999998}, {"year": 2014, "15-19": 32.45, "20-24": 113.24499999999998, "25-29": 147.79500000000002, "30-34": 121.58, "35-39": 64.985, "40-44": 24.515, "45-49": 5.130000000000001, "Oceania": 2.5486549999999992, "Place": "Oceania", "Gross Reproduction Rate": 1.25175, "Mortality Rate under 5": 18.4825, "Mortality Rate under 5 male": 20.298499999999997, "Mortality Rate under 5 female": 16.6055}, {"year": 2015, "15-19": 31.370000000000005, "20-24": 110.665, "25-29": 145.98499999999999, "30-34": 120.03000000000002, "35-39": 63.595000000000006, "40-44": 23.845, "45-49": 4.96, "Oceania": 2.5023449999999996, "Place": "Oceania", "Gross Reproduction Rate": 1.229, "Mortality Rate under 5": 17.9, "Mortality Rate under 5 male": 19.674499999999995, "Mortality Rate under 5 female": 16.073}, {"year": 2016, "15-19": 30.529999999999994, "20-24": 108.63999999999999, "25-29": 144.585, "30-34": 118.835, "35-39": 62.495000000000005, "40-44": 23.32, "45-49": 4.825, "Oceania": 2.466475, "Place": "Oceania", "Gross Reproduction Rate": 1.2111100000000001, "Mortality Rate under 5": 17.3515, "Mortality Rate under 5 male": 19.0785, "Mortality Rate under 5 female": 15.567500000000004}, {"year": 2017, "15-19": 29.709999999999997, "20-24": 106.65500000000002, "25-29": 143.215, "30-34": 117.63, "35-39": 61.44500000000001, "40-44": 22.814999999999998, "45-49": 4.67, "Oceania": 2.4306399999999995, "Place": "Oceania", "Gross Reproduction Rate": 1.19336, "Mortality Rate under 5": 16.817, "Mortality Rate under 5 male": 18.502000000000002, "Mortality Rate under 5 female": 15.079500000000001}, {"year": 2018, "15-19": 28.865, "20-24": 104.63999999999999, "25-29": 141.80999999999997, "30-34": 116.43499999999999, "35-39": 60.36499999999999, "40-44": 22.294999999999998, "45-49": 4.535, "Oceania": 2.394825, "Place": "Oceania", "Gross Reproduction Rate": 1.1753399999999998, "Mortality Rate under 5": 16.301499999999997, "Mortality Rate under 5 male": 17.944499999999994, "Mortality Rate under 5 female": 14.609}, {"year": 2019, "15-19": 28.035000000000004, "20-24": 102.64000000000001, "25-29": 140.42499999999998, "30-34": 115.25, "35-39": 59.325, "40-44": 21.794999999999998, "45-49": 4.380000000000001, "Oceania": 2.35934, "Place": "Oceania", "Gross Reproduction Rate": 1.1585299999999998, "Mortality Rate under 5": 15.805000000000003, "Mortality Rate under 5 male": 17.4025, "Mortality Rate under 5 female": 14.152499999999998}, {"year": 2020, "15-19": 27.2, "20-24": 100.645, "25-29": 139.04000000000002, "30-34": 114.06500000000001, "35-39": 58.25, "40-44": 21.29, "45-49": 4.24, "Oceania": 2.3238049999999992, "Place": "Oceania", "Gross Reproduction Rate": 1.140285, "Mortality Rate under 5": 15.317999999999998, "Mortality Rate under 5 male": 16.8785, "Mortality Rate under 5 female": 13.710500000000001}, {"year": 2021, "15-19": 26.565000000000005, "20-24": 99.16, "25-29": 138.00499999999997, "30-34": 113.20499999999997, "35-39": 57.464999999999996, "40-44": 20.93, "45-49": 4.125000000000001, "Oceania": 2.2974950000000005, "Place": "Oceania", "Gross Reproduction Rate": 1.12786, "Mortality Rate under 5": 14.860499999999998, "Mortality Rate under 5 male": 16.381500000000003, "Mortality Rate under 5 female": 13.294999999999998}, {"year": 2022, "15-19": 25.964999999999996, "20-24": 97.66, "25-29": 136.96499999999997, "30-34": 112.36499999999997, "35-39": 56.705, "40-44": 20.59, "45-49": 4.015, "Oceania": 2.271375, "Place": "Oceania", "Gross Reproduction Rate": 1.1149649999999998, "Mortality Rate under 5": 14.4175, "Mortality Rate under 5 male": 15.901999999999997, "Mortality Rate under 5 female": 12.892499999999998}, {"year": 2023, "15-19": 25.34, "20-24": 96.175, "25-29": 135.925, "30-34": 111.51999999999998, "35-39": 55.94500000000001, "40-44": 20.229999999999997, "45-49": 3.9050000000000002, "Oceania": 2.2452949999999996, "Place": "Oceania", "Gross Reproduction Rate": 1.1021449999999997, "Mortality Rate under 5": 13.992, "Mortality Rate under 5 male": 15.435500000000001, "Mortality Rate under 5 female": 12.501999999999999}, {"year": 2024, "15-19": 24.715000000000003, "20-24": 94.69, "25-29": 134.87499999999997, "30-34": 110.66499999999999, "35-39": 55.19, "40-44": 19.885, "45-49": 3.8, "Oceania": 2.21923, "Place": "Oceania", "Gross Reproduction Rate": 1.08962, "Mortality Rate under 5": 13.576500000000001, "Mortality Rate under 5 male": 14.982, "Mortality Rate under 5 female": 12.124}, {"year": 2025, "15-19": 24.095000000000006, "20-24": 93.20000000000002, "25-29": 133.83499999999998, "30-34": 109.81500000000001, "35-39": 54.44999999999999, "40-44": 19.519999999999996, "45-49": 3.7000000000000006, "Oceania": 2.1931749999999997, "Place": "Oceania", "Gross Reproduction Rate": 1.077055, "Mortality Rate under 5": 13.170499999999999, "Mortality Rate under 5 male": 14.541999999999998, "Mortality Rate under 5 female": 11.758000000000001}, {"year": 2026, "15-19": 23.645, "20-24": 92.13000000000001, "25-29": 133.075, "30-34": 109.19500000000001, "35-39": 53.925, "40-44": 19.264999999999997, "45-49": 3.625000000000001, "Oceania": 2.1743700000000006, "Place": "Oceania", "Gross Reproduction Rate": 1.067085, "Mortality Rate under 5": 12.795000000000002, "Mortality Rate under 5 male": 14.132, "Mortality Rate under 5 female": 11.414999999999997}, {"year": 2027, "15-19": 23.199999999999996, "20-24": 91.04000000000003, "25-29": 132.305, "30-34": 108.58999999999999, "35-39": 53.385000000000005, "40-44": 19.02, "45-49": 3.5450000000000004, "Oceania": 2.1555299999999997, "Place": "Oceania", "Gross Reproduction Rate": 1.05803, "Mortality Rate under 5": 12.428499999999998, "Mortality Rate under 5 male": 13.730500000000001, "Mortality Rate under 5 female": 11.084}, {"year": 2028, "15-19": 22.744999999999997, "20-24": 89.96000000000002, "25-29": 131.545, "30-34": 107.97999999999999, "35-39": 52.839999999999996, "40-44": 18.77, "45-49": 3.465, "Oceania": 2.1367000000000003, "Place": "Oceania", "Gross Reproduction Rate": 1.0490100000000002, "Mortality Rate under 5": 12.0725, "Mortality Rate under 5 male": 13.343, "Mortality Rate under 5 female": 10.763000000000002}, {"year": 2029, "15-19": 22.290000000000003, "20-24": 88.87999999999998, "25-29": 130.775, "30-34": 107.36499999999998, "35-39": 52.294999999999995, "40-44": 18.525, "45-49": 3.3900000000000006, "Oceania": 2.11787, "Place": "Oceania", "Gross Reproduction Rate": 1.03929, "Mortality Rate under 5": 11.731, "Mortality Rate under 5 male": 12.967500000000001, "Mortality Rate under 5 female": 10.452499999999999}, {"year": 2030, "15-19": 21.845, "20-24": 87.8, "25-29": 130.005, "30-34": 106.775, "35-39": 51.765, "40-44": 18.264999999999997, "45-49": 3.3050000000000006, "Oceania": 2.099055000000001, "Place": "Oceania", "Gross Reproduction Rate": 1.030135, "Mortality Rate under 5": 11.397, "Mortality Rate under 5 male": 12.602, "Mortality Rate under 5 female": 10.148999999999997}, {"year": 2031, "15-19": 21.535000000000004, "20-24": 87.055, "25-29": 129.46499999999997, "30-34": 106.36500000000001, "35-39": 51.39, "40-44": 18.119999999999997, "45-49": 3.2550000000000003, "Oceania": 2.08594, "Place": "Oceania", "Gross Reproduction Rate": 1.02363, "Mortality Rate under 5": 11.086, "Mortality Rate under 5 male": 12.261500000000002, "Mortality Rate under 5 female": 9.871500000000001}, {"year": 2032, "15-19": 21.205000000000005, "20-24": 86.27000000000001, "25-29": 128.91500000000002, "30-34": 105.93500000000002, "35-39": 51.025, "40-44": 17.945, "45-49": 3.21, "Oceania": 2.0728350000000004, "Place": "Oceania", "Gross Reproduction Rate": 1.018335, "Mortality Rate under 5": 10.7835, "Mortality Rate under 5 male": 11.9295, "Mortality Rate under 5 female": 9.6005}, {"year": 2033, "15-19": 20.885000000000005, "20-24": 85.51500000000001, "25-29": 128.38, "30-34": 105.52000000000001, "35-39": 50.67, "40-44": 17.779999999999998, "45-49": 3.165, "Oceania": 2.059745, "Place": "Oceania", "Gross Reproduction Rate": 1.0115800000000001, "Mortality Rate under 5": 10.491, "Mortality Rate under 5 male": 11.6075, "Mortality Rate under 5 female": 9.337}, {"year": 2034, "15-19": 20.580000000000002, "20-24": 84.745, "25-29": 127.85000000000002, "30-34": 105.1, "35-39": 50.309999999999995, "40-44": 17.615000000000002, "45-49": 3.1149999999999998, "Oceania": 2.04666, "Place": "Oceania", "Gross Reproduction Rate": 1.00464, "Mortality Rate under 5": 10.206999999999999, "Mortality Rate under 5 male": 11.295000000000002, "Mortality Rate under 5 female": 9.082}, {"year": 2035, "15-19": 20.259999999999998, "20-24": 83.98500000000001, "25-29": 127.29999999999998, "30-34": 104.68499999999999, "35-39": 49.955000000000005, "40-44": 17.425000000000004, "45-49": 3.075, "Oceania": 2.0335799999999997, "Place": "Oceania", "Gross Reproduction Rate": 0.9989249999999998, "Mortality Rate under 5": 9.929999999999998, "Mortality Rate under 5 male": 10.991499999999998, "Mortality Rate under 5 female": 8.8335}, {"year": 2036, "15-19": 20.035000000000004, "20-24": 83.43, "25-29": 126.91, "30-34": 104.375, "35-39": 49.68999999999999, "40-44": 17.330000000000002, "45-49": 3.0350000000000006, "Oceania": 2.02419, "Place": "Oceania", "Gross Reproduction Rate": 0.99297, "Mortality Rate under 5": 9.678, "Mortality Rate under 5 male": 10.709500000000002, "Mortality Rate under 5 female": 8.6065}, {"year": 2037, "15-19": 19.81, "20-24": 82.875, "25-29": 126.51500000000001, "30-34": 104.08, "35-39": 49.45, "40-44": 17.21, "45-49": 3.005, "Oceania": 2.014805, "Place": "Oceania", "Gross Reproduction Rate": 0.988855, "Mortality Rate under 5": 9.4265, "Mortality Rate under 5 male": 10.434999999999999, "Mortality Rate under 5 female": 8.3835}, {"year": 2038, "15-19": 19.580000000000002, "20-24": 82.33500000000001, "25-29": 126.11499999999998, "30-34": 103.785, "35-39": 49.2, "40-44": 17.099999999999998, "45-49": 2.9699999999999998, "Oceania": 2.0054349999999994, "Place": "Oceania", "Gross Reproduction Rate": 0.9838699999999998, "Mortality Rate under 5": 9.183, "Mortality Rate under 5 male": 10.1675, "Mortality Rate under 5 female": 8.1665}, {"year": 2039, "15-19": 19.35, "20-24": 81.78, "25-29": 125.725, "30-34": 103.475, "35-39": 48.93499999999999, "40-44": 16.990000000000002, "45-49": 2.9299999999999997, "Oceania": 1.9960600000000006, "Place": "Oceania", "Gross Reproduction Rate": 0.9805549999999998, "Mortality Rate under 5": 8.946000000000002, "Mortality Rate under 5 male": 9.906500000000001, "Mortality Rate under 5 female": 7.956500000000001}, {"year": 2040, "15-19": 19.119999999999997, "20-24": 81.23, "25-29": 125.33, "30-34": 103.17500000000003, "35-39": 48.7, "40-44": 16.875000000000007, "45-49": 2.8950000000000005, "Oceania": 1.9867000000000004, "Place": "Oceania", "Gross Reproduction Rate": 0.9743850000000001, "Mortality Rate under 5": 8.7185, "Mortality Rate under 5 male": 9.653500000000003, "Mortality Rate under 5 female": 7.7515}, {"year": 2041, "15-19": 18.949999999999996, "20-24": 80.805, "25-29": 125.01999999999998, "30-34": 102.94999999999997, "35-39": 48.510000000000005, "40-44": 16.785000000000004, "45-49": 2.875, "Oceania": 1.979635, "Place": "Oceania", "Gross Reproduction Rate": 0.9715150000000001, "Mortality Rate under 5": 8.506999999999998, "Mortality Rate under 5 male": 9.419500000000001, "Mortality Rate under 5 female": 7.564}, {"year": 2042, "15-19": 18.785, "20-24": 80.38500000000002, "25-29": 124.72999999999998, "30-34": 102.73000000000002, "35-39": 48.325, "40-44": 16.705, "45-49": 2.86, "Oceania": 1.9725450000000002, "Place": "Oceania", "Gross Reproduction Rate": 0.9672750000000002, "Mortality Rate under 5": 8.3, "Mortality Rate under 5 male": 9.191999999999998, "Mortality Rate under 5 female": 7.381500000000003}, {"year": 2043, "15-19": 18.6, "20-24": 79.975, "25-29": 124.41499999999999, "30-34": 102.48499999999999, "35-39": 48.13, "40-44": 16.625, "45-49": 2.8199999999999994, "Oceania": 1.965465, "Place": "Oceania", "Gross Reproduction Rate": 0.9646299999999999, "Mortality Rate under 5": 8.101, "Mortality Rate under 5 male": 8.971500000000002, "Mortality Rate under 5 female": 7.203500000000003}, {"year": 2044, "15-19": 18.435000000000002, "20-24": 79.55, "25-29": 124.12, "30-34": 102.26500000000001, "35-39": 47.94499999999999, "40-44": 16.540000000000003, "45-49": 2.8049999999999993, "Oceania": 1.9583699999999997, "Place": "Oceania", "Gross Reproduction Rate": 0.962045, "Mortality Rate under 5": 7.906499999999999, "Mortality Rate under 5 male": 8.753, "Mortality Rate under 5 female": 7.030000000000001}, {"year": 2045, "15-19": 18.259999999999998, "20-24": 79.13000000000002, "25-29": 123.80999999999999, "30-34": 102.03999999999999, "35-39": 47.745000000000005, "40-44": 16.464999999999996, "45-49": 2.77, "Oceania": 1.9512899999999997, "Place": "Oceania", "Gross Reproduction Rate": 0.9574250000000001, "Mortality Rate under 5": 7.715000000000001, "Mortality Rate under 5 male": 8.542499999999999, "Mortality Rate under 5 female": 6.8595}, {"year": 2046, "15-19": 18.124999999999996, "20-24": 78.83, "25-29": 123.59999999999998, "30-34": 101.86500000000001, "35-39": 47.61, "40-44": 16.404999999999998, "45-49": 2.755, "Oceania": 1.94612, "Place": "Oceania", "Gross Reproduction Rate": 0.9548850000000002, "Mortality Rate under 5": 7.540499999999999, "Mortality Rate under 5 male": 8.349499999999999, "Mortality Rate under 5 female": 6.706000000000001}, {"year": 2047, "15-19": 17.995, "20-24": 78.53500000000001, "25-29": 123.38000000000002, "30-34": 101.68999999999998, "35-39": 47.464999999999996, "40-44": 16.345000000000002, "45-49": 2.75, "Oceania": 1.9409350000000003, "Place": "Oceania", "Gross Reproduction Rate": 0.95153, "Mortality Rate under 5": 7.372, "Mortality Rate under 5 male": 8.161, "Mortality Rate under 5 female": 6.557}, {"year": 2048, "15-19": 17.87, "20-24": 78.22000000000001, "25-29": 123.15499999999997, "30-34": 101.51000000000002, "35-39": 47.325, "40-44": 16.29, "45-49": 2.73, "Oceania": 1.9357499999999999, "Place": "Oceania", "Gross Reproduction Rate": 0.94931, "Mortality Rate under 5": 7.204499999999999, "Mortality Rate under 5 male": 7.9765000000000015, "Mortality Rate under 5 female": 6.411}, {"year": 2049, "15-19": 17.749999999999996, "20-24": 77.925, "25-29": 122.95, "30-34": 101.33, "35-39": 47.19500000000001, "40-44": 16.215, "45-49": 2.715, "Oceania": 1.9305700000000001, "Place": "Oceania", "Gross Reproduction Rate": 0.947855, "Mortality Rate under 5": 7.0424999999999995, "Mortality Rate under 5 male": 7.794499999999999, "Mortality Rate under 5 female": 6.2685}, {"year": 2050, "15-19": 17.625, "20-24": 77.63500000000002, "25-29": 122.725, "30-34": 101.16499999999999, "35-39": 47.040000000000006, "40-44": 16.17, "45-49": 2.6999999999999997, "Oceania": 1.925375, "Place": "Oceania", "Gross Reproduction Rate": 0.9445, "Mortality Rate under 5": 6.883999999999999, "Mortality Rate under 5 male": 7.617, "Mortality Rate under 5 female": 6.128}]}